ansys/grantami/bomanalytics/__init__.py
ansys/grantami/bomanalytics/_allowed_types.py
ansys/grantami/bomanalytics/_bom_helper.py
ansys/grantami/bomanalytics/_connection.py
ansys/grantami/bomanalytics/_exceptions.py
ansys/grantami/bomanalytics/_item_definitions.py
ansys/grantami/bomanalytics/_item_results.py
ansys/grantami/bomanalytics/_logger.py
ansys/grantami/bomanalytics/_query_results.py
ansys/grantami/bomanalytics/_typing.py
ansys/grantami/bomanalytics/bom_types/__init__.py
ansys/grantami/bomanalytics/bom_types/_base_types.py
ansys/grantami/bomanalytics/bom_types/_bom_reader.py
ansys/grantami/bomanalytics/bom_types/_bom_writer.py
ansys/grantami/bomanalytics/bom_types/_builders.py
ansys/grantami/bomanalytics/bom_types/eco2301/__init__.py
ansys/grantami/bomanalytics/bom_types/eco2301/_bom_reader.py
ansys/grantami/bomanalytics/bom_types/eco2301/_bom_types.py
ansys/grantami/bomanalytics/bom_types/eco2301/_bom_writer.py
ansys/grantami/bomanalytics/bom_types/eco2412/__init__.py
ansys/grantami/bomanalytics/bom_types/eco2412/_bom_reader.py
ansys/grantami/bomanalytics/bom_types/eco2412/_bom_types.py
ansys/grantami/bomanalytics/bom_types/eco2412/_bom_writer.py
ansys/grantami/bomanalytics/bom_types/gbt1205/__init__.py
ansys/grantami/bomanalytics/bom_types/gbt1205/_bom_types.py
ansys/grantami/bomanalytics/indicators.py
ansys/grantami/bomanalytics/py.typed
ansys/grantami/bomanalytics/queries.py
ansys/grantami/bomanalytics/schemas/BillOfMaterialsEco1711.xsd
ansys/grantami/bomanalytics/schemas/BillOfMaterialsEco2301.xsd
ansys/grantami/bomanalytics/schemas/BillOfMaterialsEco2412.xsd
ansys/grantami/bomanalytics/schemas/__init__.py
ansys/grantami/bomanalytics/schemas/grantarecord1205.xsd
ansys_grantami_bomanalytics-2.3.1.dist-info/AUTHORS
ansys_grantami_bomanalytics-2.3.1.dist-info/LICENSE
ansys_grantami_bomanalytics-2.3.1.dist-info/METADATA
ansys_grantami_bomanalytics-2.3.1.dist-info/WHEEL
ansys_grantami_bomanalytics-2.3.1.dist-info/RECORD
