Metadata-Version: 2.3
Name: ansys-grantami-bomanalytics
Version: 2.3.1
Summary: Perform compliance and sustainability analysis on materials data stored in Granta MI.
License: MIT
Keywords: Ansys,Granta MI,Bill of Materials
Author: ANSYS, Inc.
Author-email: pyansys.core@ansys.com
Maintainer: ANSYS, Inc.
Maintainer-email: pyansys.core@ansys.com
Requires-Python: >=3.10.0,<4.0.0
Classifier: Development Status :: 5 - Production/Stable
Classifier: Intended Audience :: Science/Research
Classifier: License :: OSI Approved :: MIT License
Classifier: Operating System :: MacOS
Classifier: Operating System :: Microsoft :: Windows
Classifier: Operating System :: POSIX
Classifier: Programming Language :: Python :: 3
Classifier: Programming Language :: Python :: 3.10
Classifier: Programming Language :: Python :: 3.11
Classifier: Programming Language :: Python :: 3.12
Classifier: Programming Language :: Python :: 3.13
Classifier: Topic :: Scientific/Engineering :: Information Analysis
Provides-Extra: examples
Requires-Dist: ansys-grantami-bomanalytics-openapi (>=4.0,<5.0)
Requires-Dist: ansys-openapi-common (>=2.0.0,<3.0.0)
Requires-Dist: ipywidgets (>=8.1.1,<9.0.0) ; extra == "examples"
Requires-Dist: jupyterlab (>=3,<5) ; extra == "examples"
Requires-Dist: lxml (>=4,<6) ; extra == "examples"
Requires-Dist: pandas (>=2.0,<3.0) ; extra == "examples"
Requires-Dist: plotly (>=5.17,<7.0) ; extra == "examples"
Requires-Dist: tabulate (>=0.9,<0.10) ; extra == "examples"
Requires-Dist: xmlschema (>=3.0.1,<5.0)
Project-URL: Documentation, https://bomanalytics.grantami.docs.pyansys.com
Project-URL: Repository, https://github.com/ansys/grantami-bomanalytics
